MANIFEST.in
README.md
setup.py
data/__init__.py
data/load_data.py
data/__pycache__/__init__.cpython-37.pyc
data/__pycache__/load_data.cpython-37.pyc
data/html/basic.tpl
data/html/full.tpl
data/html/mathjax.tpl
data/html/slides_reveal.tpl
data/latex/article.tplx
data/latex/base.tplx
data/latex/style_jupyter.tplx
data/latex/style_notebook.tplx
expy/__init__.py
expy/__main__.py
expy/base.py
expy/calc.py
expy/core.py
expy/disp.py
expy/latex.py
expy/tex.py
expy/var.py
expy_python.egg-info/PKG-INFO
expy_python.egg-info/SOURCES.txt
expy_python.egg-info/dependency_links.txt
expy_python.egg-info/entry_points.txt
expy_python.egg-info/top_level.txt
nbc/__init__.py
nbc/__main__.py
nbc/nbc.py
options/__init__.py
options/nbc_options.py
test/__init__.py