Metadata-Version: 2.1
Name: expy-python
Version: 1.0.0
Summary: The sophisticated tool needed for scientific computing.
Home-page: https://github.com/YouseiTakei/expy
Author: Yousei
Author-email: yousei_san@icloud.com
License: UNKNOWN
Keywords: expy
Platform: UNKNOWN
Classifier: Development Status :: 2 - Pre-Alpha
Classifier: Natural Language :: English
Classifier: License :: OSI Approved :: MIT License
Classifier: Programming Language :: Python :: 3.6
Classifier: Operating System :: OS Independent
